Metadata-Version: 2.1
Name: nxbt
Version: 0.1.4
Summary: Control your Nintendo Switch through a website, terminal, or macro.
Home-page: https://pypi.python.org/pypi/nxbt
Author: Reece Walsh
Author-email: reece@brikwerk.com
License: MIT
Project-URL: Code, https://github.com/Brikwerk/nxbt
Project-URL: Issue tracker, https://github.com/Brikwerk/nxbt/issues
Platform: any
Classifier: Development Status :: 3 - Alpha
Classifier: Intended Audience :: Developers
Classifier: License :: OSI Approved :: MIT License
Classifier: Operating System :: OS Independent
Classifier: Programming Language :: Python
Classifier: Programming Language :: Python :: 3.6
Classifier: Programming Language :: Python :: 3.7
Classifier: Programming Language :: Python :: 3.8
Classifier: Topic :: Software Development :: Libraries :: Python Modules
Requires-Python: >=3.6
License-File: LICENSE
Requires-Dist: dbus-python (==1.2.16)
Requires-Dist: Flask (==1.1.2)
Requires-Dist: Flask-SocketIO (==5.0.1)
Requires-Dist: eventlet (==0.31.0)
Requires-Dist: blessed (==1.17.10)
Requires-Dist: pynput (==1.7.1)
Requires-Dist: psutil (==5.6.6)
Requires-Dist: cryptography (==3.3.2)
